sen_api/__init__.py
sen_api/__main__.py
sen_api/cli.py
sen_api/config.py
sen_api/exceptions.py
sen_api/models.py
sen_api/provider.py
sen_api/utils.py
sen_api-0.1.3.dist-info/LICENSE
sen_api-0.1.3.dist-info/METADATA
sen_api-0.1.3.dist-info/WHEEL
sen_api-0.1.3.dist-info/entry_points.txt
sen_api-0.1.3.dist-info/top_level.txt
sen_api-0.1.3.dist-info/RECORD
