Metadata-Version: 2.1
Name: sen-api
Version: 0.1.3
Summary: UNKNOWN
Home-page: UNKNOWN
Author: Marco Volpato
License: UNKNOWN
Platform: UNKNOWN
Requires-Python: >=3.6
Requires-Dist: requests
Requires-Dist: beautifulsoup4
Requires-Dist: click
Requires-Dist: halo
Requires-Dist: loguru
Requires-Dist: rich
